llm_docgen/__init__.py
llm_docgen/cli/__init__.py
llm_docgen/cli/commands.py
llm_docgen/parsers/__init__.py
llm_docgen/parsers/python_parser.py
simplepydoc-0.1.2.dist-info/LICENSE
simplepydoc-0.1.2.dist-info/METADATA
simplepydoc-0.1.2.dist-info/WHEEL
simplepydoc-0.1.2.dist-info/entry_points.txt
simplepydoc-0.1.2.dist-info/RECORD
