Metadata-Version: 2.1
Name: simplepydoc
Version: 0.1.2
Summary: Simple Python documentation generator - parse code, generate markdown
Home-page: https://github.com/msodiq19/simplepydoc
License: MIT
Keywords: documentation,python,markdown,docstring,ast,api-docs
Author: Sodiq Muhammed
Author-email: muhammedsodiq2018@gmail.com
Requires-Python: >=3.9,<4.0
Classifier: Development Status :: 4 - Beta
Classifier: Intended Audience :: Developers
Classifier: License :: OSI Approved :: MIT License
Classifier: Programming Language :: Python :: 3
Classifier: Programming Language :: Python :: 3.9
Classifier: Programming Language :: Python :: 3.10
Classifier: Programming Language :: Python :: 3.11
Classifier: Programming Language :: Python :: 3.12
Classifier: Topic :: Documentation
Classifier: Topic :: Software Development :: Documentation
Requires-Dist: click (>=8.1.7,<9.0.0)
Project-URL: Repository, https://github.com/msodiq19/simplepydoc
